{
    "_links": {
        "related-artworks": [
            {
                "href": "http://scrapi.org/object/22247"
            },
            {
                "href": "http://scrapi.org/object/25385"
            },
            {
                "href": "http://scrapi.org/object/26436"
            },
            {
                "href": "http://scrapi.org/object/26437"
            },
            {
                "href": "http://scrapi.org/object/25120"
            }
        ],
        "related-content": [
            {
                "date": "From October 2, 2012",
                "href": "/exhibitions/listings/2012/arms-and-armor",
                "rel": "Bashford Dean and the Creation of the Arms and Armor Department"
            },
            {
                "date": "March 15, 2014",
                "href": "/events/programs/tours/arms-and-armor?eid=A074_%7bED560830-C78D-4979-8EDE-EEC11BA7BE61%7d_20131126112917",
                "rel": "Arms and Armor"
            },
            {
                "date": "March 22, 2014",
                "href": "/events/programs/tours/arms-and-armor?eid=A084_%7bED560830-C78D-4979-8EDE-EEC11BA7BE61%7d_20131126113556",
                "rel": "Arms and Armor"
            },
            {
                "date": "March 23, 2014",
                "href": "/events/programs/tours/arms-and-armor?eid=A093_%7bED560830-C78D-4979-8EDE-EEC11BA7BE61%7d_20131126113923",
                "rel": "Arms and Armor"
            },
            {
                "date": "March 29, 2014",
                "href": "/events/programs/tours/arms-and-armor?eid=A075_%7bED560830-C78D-4979-8EDE-EEC11BA7BE61%7d_20131126112932",
                "rel": "Arms and Armor"
            },
            {
                "date": "March 30, 2014",
                "href": "/events/programs/tours/arms-and-armor?eid=A094_%7bED560830-C78D-4979-8EDE-EEC11BA7BE61%7d_20131126113938",
                "rel": "Arms and Armor"
            },
            {
                "date": "April 5, 2014",
                "href": "/events/programs/tours/arms-and-armor?eid=A085_%7bED560830-C78D-4979-8EDE-EEC11BA7BE61%7d_20131126113610",
                "rel": "Arms and Armor"
            },
            {
                "date": "April 12, 2014",
                "href": "/events/programs/art-making-programs/studio-workshops/metal-working-armor-inspired?eid=A002_%7bD4D82B5D-B826-4415-8C88-3C64B7AECB22%7d_20140109161351",
                "rel": "Metal Working: Armor-Inspired Jewelry and Sculpture"
            },
            {
                "date": "April 12, 2014",
                "href": "/events/programs/tours/arms-and-armor?eid=A076_%7bED560830-C78D-4979-8EDE-EEC11BA7BE61%7d_20131126112951",
                "rel": "Arms and Armor"
            },
            {
                "date": "April 19, 2014",
                "href": "/events/programs/art-making-programs/studio-workshops/metal-working-armor-inspired?eid=A002_%7bD4D82B5D-B826-4415-8C88-3C64B7AECB22%7d_20140109161305",
                "rel": "Metal Working: Armor-Inspired Jewelry and Sculpture"
            },
            {
                "date": "April 26, 2014",
                "href": "/events/programs/tours/arms-and-armor?eid=A086_%7bED560830-C78D-4979-8EDE-EEC11BA7BE61%7d_20131126113630",
                "rel": "Arms and Armor"
            },
            {
                "date": "",
                "href": "http://www.metmuseum.org/toah/ht/?period=08\u00aeion=eustn",
                "rel": "Venice and Northern Italy, 1400\u20131600 A.D."
            },
            {
                "date": "",
                "href": "http://www.metmuseum.org/toah/ht/?period=09\u00aeion=eustn",
                "rel": "Venice and Northern Italy, 1600\u20131800 A.D."
            }
        ],
        "self": {
            "href": "http://scrapi.org/object/26512"
        },
        "source": {
            "href": "http://www.metmuseum.org/Collections/search-the-collections/26512"
        }
    },
    "accession number": "14.25.532",
    "credit line": "Gift of William H. Riggs, 1913",
    "culture": "Italian, Brescia",
    "date": "ca. 1570\u201380",
    "department": "Arms and Armor",
    "dimensions": "H. 10 5/8 in. (27 cm); W. 9 3/8 in. (23.81 cm); Wt. 3 lb. 3 oz. (1449 g)",
    "id": 26512,
    "image": "http://images.metmuseum.org/CRDImages/aa/original/DP22369.jpg",
    "medium": "Steel, brass",
    "provenance": [
        "Ex colls.:  Auguste Henry, Paris",
        "William H. Riggs, Paris"
    ],
    "title": "Pointed Morion",
    "what": [
        "Metal",
        "Costume",
        "Copper alloy",
        "Iron and iron alloy",
        "Iron alloy",
        "Steel",
        "Brass",
        "Armor",
        "Body armor",
        "Helmets",
        "Morions"
    ],
    "where": [
        "Europe",
        "Italy",
        "Lombardy",
        "Brescia"
    ]
}