{
    "_links": {
        "related-artworks": [
            {
                "href": "http://scrapi.org/object/131888"
            },
            {
                "href": "http://scrapi.org/object/134423"
            },
            {
                "href": "http://scrapi.org/object/127643"
            },
            {
                "href": "http://scrapi.org/object/127644"
            },
            {
                "href": "http://scrapi.org/object/127645"
            }
        ],
        "related-content": [
            {
                "date": "From May 8, 2014",
                "href": "/exhibitions/listings/2014/charles-james",
                "rel": "Charles James: Beyond Fashion"
            },
            {
                "date": "March 11, 2014",
                "href": "/events/programs/tours/fashion-in-art?eid=R131_%7b84F1FA41-DCF8-456F-B475-64003655E84E%7d_20140311130000",
                "rel": "Fashion in Art"
            },
            {
                "date": "March 12, 2014",
                "href": "/events/programs/tours/fashion-in-art?eid=R132_%7b84F1FA41-DCF8-456F-B475-64003655E84E%7d_20140312130000",
                "rel": "Fashion in Art"
            },
            {
                "date": "March 13, 2014",
                "href": "/events/programs/tours/fashion-in-art?eid=R133_%7b84F1FA41-DCF8-456F-B475-64003655E84E%7d_20140313130000",
                "rel": "Fashion in Art"
            },
            {
                "date": "March 14, 2014",
                "href": "/events/programs/tours/fashion-in-art?eid=R134_%7b84F1FA41-DCF8-456F-B475-64003655E84E%7d_20140314130000",
                "rel": "Fashion in Art"
            },
            {
                "date": "March 31, 2014",
                "href": "/events/programs/tours/fashion-in-art?eid=R145_%7b84F1FA41-DCF8-456F-B475-64003655E84E%7d_20140331130000",
                "rel": "Fashion in Art"
            },
            {
                "date": "April 1, 2014",
                "href": "/events/programs/tours/fashion-in-art?eid=R146_%7b84F1FA41-DCF8-456F-B475-64003655E84E%7d_20140401130000",
                "rel": "Fashion in Art"
            },
            {
                "date": "April 2, 2014",
                "href": "/events/programs/tours/fashion-in-art?eid=R147_%7b84F1FA41-DCF8-456F-B475-64003655E84E%7d_20140402130000",
                "rel": "Fashion in Art"
            },
            {
                "date": "April 3, 2014",
                "href": "/events/programs/tours/fashion-in-art?eid=R148_%7b84F1FA41-DCF8-456F-B475-64003655E84E%7d_20140403130000",
                "rel": "Fashion in Art"
            },
            {
                "date": "April 4, 2014",
                "href": "/events/programs/tours/fashion-in-art?eid=R149_%7b84F1FA41-DCF8-456F-B475-64003655E84E%7d_20140404130000",
                "rel": "Fashion in Art"
            },
            {
                "date": "April 7, 2014",
                "href": "/events/programs/tours/fashion-in-art?eid=R150_%7b84F1FA41-DCF8-456F-B475-64003655E84E%7d_20140407130000",
                "rel": "Fashion in Art"
            },
            {
                "date": "",
                "href": "http://www.metmuseum.org/toah/hd/cost/hd_cost.htm",
                "rel": "Costume in The Metropolitan Museum of Art"
            },
            {
                "date": "",
                "href": "http://www.metmuseum.org/toah/hd/coho/hd_coho.htm",
                "rel": "Dressing for the Cocktail Hour"
            },
            {
                "date": "",
                "href": "http://www.metmuseum.org/toah/hd/chnl/hd_chnl.htm",
                "rel": "Gabrielle \"Coco\" Chanel (1883\u20131971) and the House of Chanel"
            },
            {
                "date": "",
                "href": "http://www.metmuseum.org/toah/ht/?period=11\u00aeion=euwf",
                "rel": "France, 1900 A.D.\u2013present"
            }
        ],
        "self": {
            "href": "http://scrapi.org/object/131891"
        },
        "source": {
            "href": "http://www.metmuseum.org/Collections/search-the-collections/131891"
        }
    },
    "accession number": "2006.420.161",
    "credit line": "Gift of Thomas L. Kempner, 2006",
    "culture": "French",
    "date": "ca. 1990",
    "department": "Costume Institute",
    "dimensions": "Length 38 in. (96.5 cm)",
    "id": 131891,
    "image": "http://images.metmuseum.org/CRDImages/ci/original/TR.171.1670.2006.jpg",
    "medium": "wood, brass",
    "title": "Belt",
    "what": [
        "Metal",
        "Costume",
        "Copper alloy",
        "Brass",
        "Belts"
    ],
    "when": "A.D. 1900-present",
    "where": [
        "Europe",
        "France"
    ],
    "who": "House of Chanel"
}